{
  "emily@fansy.cz": {
    "sales": "Джеля",
    "type": "workspace",
    "status": "ok",
    "error": null,
    "last_check": "2026-04-12 07:00:10",
    "messages_total": 54021
  },
  "katrin@fansy.cz": {
    "sales": "Джеля",
    "type": "workspace",
    "status": "ok",
    "error": null,
    "last_check": "2026-04-12 07:00:11",
    "messages_total": 225549
  },
  "emily@inperson.agency": {
    "sales": "Джеля",
    "type": "workspace",
    "status": "ok",
    "error": null,
    "last_check": "2026-04-12 07:00:12",
    "messages_total": 284408
  },
  "sophia@inperson-group.com": {
    "sales": "Джеля",
    "type": "workspace",
    "status": "ok",
    "error": null,
    "last_check": "2026-04-12 07:00:13",
    "messages_total": 17267
  },
  "annie@inperson.agency": {
    "sales": "Настя",
    "type": "workspace",
    "status": "ok",
    "error": null,
    "last_check": "2026-04-12 07:00:16",
    "messages_total": 64798
  },
  "annie@inperson-group.com": {
    "sales": "Настя",
    "type": "workspace",
    "status": "ok",
    "error": null,
    "last_check": "2026-04-12 07:00:18",
    "messages_total": 8846
  },
  "amelia@inperson-group.com": {
    "sales": "Ксения",
    "type": "workspace",
    "status": "ok",
    "error": null,
    "last_check": "2026-04-12 07:00:20",
    "messages_total": 6686
  },
  "milukovasofia457@gmail.com": {
    "sales": "Джеля",
    "type": "gmail",
    "status": "ok",
    "error": null,
    "last_check": "2026-04-12 07:00:22",
    "messages_total": 9905
  },
  "aalexantoos@gmail.com": {
    "sales": "Джеля",
    "type": "gmail",
    "status": "ok",
    "error": null,
    "last_check": "2026-04-12 07:00:23",
    "messages_total": 13779
  },
  "gachakeril@gmail.com": {
    "sales": "Джеля",
    "type": "gmail",
    "status": "ok",
    "error": null,
    "last_check": "2026-04-12 07:00:24",
    "messages_total": 20859
  },
  "mijaresenely523@gmail.com": {
    "sales": "Джеля",
    "type": "gmail",
    "status": "ok",
    "error": null,
    "last_check": "2026-04-12 07:00:25",
    "messages_total": 23147
  },
  "klavarossi@gmail.com": {
    "sales": "Джеля",
    "type": "gmail",
    "status": "ok",
    "error": null,
    "last_check": "2026-04-12 07:00:25",
    "messages_total": 24127
  },
  "annwalkmanmgmt@gmail.com": {
    "sales": "Настя",
    "type": "gmail",
    "status": "ok",
    "error": null,
    "last_check": "2026-04-12 07:00:26",
    "messages_total": 1916
  },
  "walkman.annie@gmail.com": {
    "sales": "Настя",
    "type": "gmail",
    "status": "ok",
    "error": null,
    "last_check": "2026-04-12 07:00:27",
    "messages_total": 27438
  },
  "annie.applin@gmail.com": {
    "sales": "Настя",
    "type": "gmail",
    "status": "ok",
    "error": null,
    "last_check": "2026-04-12 07:00:28",
    "messages_total": 2
  },
  "ann.gruv@gmail.com": {
    "sales": "Настя",
    "type": "gmail",
    "status": "ok",
    "error": null,
    "last_check": "2026-04-12 07:00:28",
    "messages_total": 585
  },
  "tammy.melloww@gmail.com": {
    "sales": "Настя",
    "type": "gmail",
    "status": "ok",
    "error": null,
    "last_check": "2026-04-12 07:00:29",
    "messages_total": 32236
  },
  "oliviamerrickson@gmail.com": {
    "sales": "Настя",
    "type": "gmail",
    "status": "ok",
    "error": null,
    "last_check": "2026-04-12 07:00:30",
    "messages_total": 33
  },
  "roksiblackfansy@gmail.com": {
    "sales": "Ксения",
    "type": "gmail",
    "status": "ok",
    "error": null,
    "last_check": "2026-04-12 07:00:31",
    "messages_total": 32236
  },
  "roxanawinterhold@gmail.com": {
    "sales": "Ксения",
    "type": "gmail",
    "status": "ok",
    "error": null,
    "last_check": "2026-04-12 07:00:31",
    "messages_total": 7412
  },
  "roxanabarnum@gmail.com": {
    "sales": "Ксения",
    "type": "gmail",
    "status": "ok",
    "error": null,
    "last_check": "2026-04-12 07:00:32",
    "messages_total": 342
  },
  "blueskyroxana@gmail.com": {
    "sales": "Ксения",
    "type": "gmail",
    "status": "ok",
    "error": null,
    "last_check": "2026-04-12 07:00:33",
    "messages_total": 356
  },
  "woodenwarekristian@gmail.com": {
    "sales": "Ксения",
    "type": "gmail",
    "status": "ok",
    "error": null,
    "last_check": "2026-04-12 07:00:34",
    "messages_total": 304
  }
}